django_broadcaster/__init__.py
django_broadcaster/admin.py
django_broadcaster/apps.py
django_broadcaster/backends.py
django_broadcaster/events.py
django_broadcaster/models.py
django_broadcaster/publishers.py
django_broadcaster/registry.py
django_broadcaster/signals.py
django_broadcaster/management/__init__.py
django_broadcaster/management/commands/__init__.py
django_broadcaster/management/commands/outbox_worker.py
django_broadcaster/migrations/0001_initial.py
django_broadcaster/migrations/__init__.py
django_broadcaster-0.1.1.dist-info/METADATA
django_broadcaster-0.1.1.dist-info/WHEEL
django_broadcaster-0.1.1.dist-info/entry_points.txt
django_broadcaster-0.1.1.dist-info/licenses/LICENSE
django_broadcaster-0.1.1.dist-info/RECORD
