Metadata-Version: 2.4
Name: django-broadcaster
Version: 0.1.1
Summary: A Django app implementing the transactional outbox pattern with CloudEvents support
Project-URL: Homepage, https://github.com/mrb101/django_broadcaster
Project-URL: Repository, https://github.com/mrb101/django_broadcaster
Project-URL: Documentation, https://django-broadcaster.readthedocs.io
Project-URL: Bug Tracker, https://github.com/mrb101/django_broadcaster/issues
Author-email: "Bassel J. Hamadeh" <hamadeh.basel@gmail.com>
Maintainer-email: "Bassel J. Hamadeh" <hamadeh.basel@gmail.com>
License-Expression: MIT
License-File: LICENSE
Keywords: broadcast,dispatch,django,events,outbox
Classifier: Development Status :: 4 - Beta
Classifier: Environment :: Web Environment
Classifier: Framework :: Django
Classifier: Framework :: Django :: 4.1
Classifier: Framework :: Django :: 4.2
Classifier: Framework :: Django :: 5.0
Classifier: Intended Audience :: Developers
Classifier: License :: OSI Approved :: MIT License
Classifier: Operating System :: OS Independent
Classifier: Programming Language :: Python
Classifier: Programming Language :: Python :: 3
Classifier: Programming Language :: Python :: 3.11
Classifier: Programming Language :: Python :: 3.12
Classifier: Programming Language :: Python :: 3.13
Classifier: Topic :: Internet :: WWW/HTTP
Classifier: Topic :: Software Development :: Libraries :: Python Modules
Classifier: Topic :: System :: Distributed Computing
Requires-Python: >=3.11
Requires-Dist: django>=4.2.0
Requires-Dist: redis>=6.2.0
Provides-Extra: dev
Requires-Dist: black>=25.1.0; extra == 'dev'
Requires-Dist: pytest-django>=4.11.1; extra == 'dev'
Requires-Dist: pytest>=8.4.1; extra == 'dev'
Requires-Dist: ruff>=0.12.0; extra == 'dev'
Provides-Extra: docs
Requires-Dist: sphinx-autodoc-typehints>=1.22.0; extra == 'docs'
Requires-Dist: sphinx-rtd-theme>=1.2.0; extra == 'docs'
Requires-Dist: sphinx>=6.0.0; extra == 'docs'
